python_opensky/__init__.py
python_opensky/const.py
python_opensky/exceptions.py
python_opensky/models.py
python_opensky/opensky.py
python_opensky/py.typed
python_opensky/util.py
python_opensky-1.0.0.dist-info/LICENSE.md
python_opensky-1.0.0.dist-info/METADATA
python_opensky-1.0.0.dist-info/WHEEL
python_opensky-1.0.0.dist-info/RECORD
